{"AW":{"alpha2":"AW","alpha3":"ABW","name":"Aruba","official_name":"Aruba","flag":"🇦🇼","region":"Americas","subregion":"Caribbean","capital":"Oranjestad","latlng":[12.5,-69.96666666],"currency":{"code":"AWG","name":"Aruban florin","symbol":"ƒ"},"dialing_code":"+2","tld":".aw"},"AF":{"alpha2":"AF","alpha3":"AFG","name":"Afghanistan","official_name":"Islamic Republic of Afghanistan","flag":"🇦🇫","region":"Asia","subregion":"Southern Asia","capital":"Kabul","latlng":[33,65],"currency":{"code":"AFN","name":"Afghan afghani","symbol":"؋"},"dialing_code":"+9","tld":".af"},"AO":{"alpha2":"AO","alpha3":"AGO","name":"Angola","official_name":"Republic of Angola","flag":"🇦🇴","region":"Africa","subregion":"Middle Africa","capital":"Luanda","latlng":[-12.5,18.5],"currency":{"code":"AOA","name":"Angolan kwanza","symbol":"Kz"},"dialing_code":"+2","tld":".ao"},"AI":{"alpha2":"AI","alpha3":"AIA","name":"Anguilla","official_name":"Anguilla","flag":"🇦🇮","region":"Americas","subregion":"Caribbean","capital":"The Valley","latlng":[18.25,-63.16666666],"currency":{"code":"XCD","name":"Eastern Caribbean dollar","symbol":"$"},"dialing_code":"+1","tld":".ai"},"AX":{"alpha2":"AX","alpha3":"ALA","name":"Åland Islands","official_name":"Åland Islands","flag":"🇦🇽","region":"Europe","subregion":"Northern Europe","capital":"Mariehamn","latlng":[60.116667,19.9],"currency":{"code":"EUR","name":"Euro","symbol":"€"},"dialing_code":"+3","tld":".ax"},"AL":{"alpha2":"AL","alpha3":"ALB","name":"Albania","official_name":"Republic of Albania","flag":"🇦🇱","region":"Europe","subregion":"Southeast Europe","capital":"Tirana","latlng":[41,20],"currency":{"code":"ALL","name":"Albanian lek","symbol":"L"},"dialing_code":"+3","tld":".al"},"AD":{"alpha2":"AD","alpha3":"AND","name":"Andorra","official_name":"Principality of Andorra","flag":"🇦🇩","region":"Europe","subregion":"Southern Europe","capital":"Andorra la Vella","latlng":[42.5,1.5],"currency":{"code":"EUR","name":"Euro","symbol":"€"},"dialing_code":"+3","tld":".ad"},"AE":{"alpha2":"AE","alpha3":"ARE","name":"United Arab Emirates","official_name":"United Arab Emirates","flag":"🇦🇪","region":"Asia","subregion":"Western Asia","capital":"Abu Dhabi","latlng":[24,54],"currency":{"code":"AED","name":"United Arab Emirates dirham","symbol":"د.إ"},"dialing_code":"+9","tld":".ae"},"AR":{"alpha2":"AR","alpha3":"ARG","name":"Argentina","official_name":"Argentine Republic","flag":"🇦🇷","region":"Americas","subregion":"South America","capital":"Buenos Aires","latlng":[-34,-64],"currency":{"code":"ARS","name":"Argentine peso","symbol":"$"},"dialing_code":"+5","tld":".ar"},"AM":{"alpha2":"AM","alpha3":"ARM","name":"Armenia","official_name":"Republic of Armenia","flag":"🇦🇲","region":"Asia","subregion":"Western Asia","capital":"Yerevan","latlng":[40,45],"currency":{"code":"AMD","name":"Armenian dram","symbol":"֏"},"dialing_code":"+3","tld":".am"},"AS":{"alpha2":"AS","alpha3":"ASM","name":"American Samoa","official_name":"American Samoa","flag":"🇦🇸","region":"Oceania","subregion":"Polynesia","capital":"Pago Pago","latlng":[-14.33333333,-170],"currency":{"code":"USD","name":"United States dollar","symbol":"$"},"dialing_code":"+1","tld":".as"},"AQ":{"alpha2":"AQ","alpha3":"ATA","name":"Antarctica","official_name":"Antarctica","flag":"🇦🇶","region":"Antarctic","subregion":null,"capital":null,"latlng":[-90,0],"currency":null,"dialing_code":null,"tld":".aq"},"TF":{"alpha2":"TF","alpha3":"ATF","name":"French Southern and Antarctic Lands","official_name":"Territory of the French Southern and Antarctic Lands","flag":"🇹🇫","region":"Antarctic","subregion":null,"capital":"Port-aux-Français","latlng":[-49.25,69.167],"currency":{"code":"EUR","name":"Euro","symbol":"€"},"dialing_code":"+2","tld":".tf"},"AG":{"alpha2":"AG","alpha3":"ATG","name":"Antigua and Barbuda","official_name":"Antigua and Barbuda","flag":"🇦🇬","region":"Americas","subregion":"Caribbean","capital":"Saint John's","latlng":[17.05,-61.8],"currency":{"code":"XCD","name":"Eastern Caribbean dollar","symbol":"$"},"dialing_code":"+1","tld":".ag"},"AU":{"alpha2":"AU","alpha3":"AUS","name":"Australia","official_name":"Commonwealth of Australia","flag":"🇦🇺","region":"Oceania","subregion":"Australia and New Zealand","capital":"Canberra","latlng":[-27,133],"currency":{"code":"AUD","name":"Australian dollar","symbol":"$"},"dialing_code":"+6","tld":".au"},"AT":{"alpha2":"AT","alpha3":"AUT","name":"Austria","official_name":"Republic of Austria","flag":"🇦🇹","region":"Europe","subregion":"Central Europe","capital":"Vienna","latlng":[47.33333333,13.33333333],"currency":{"code":"EUR","name":"Euro","symbol":"€"},"dialing_code":"+4","tld":".at"},"AZ":{"alpha2":"AZ","alpha3":"AZE","name":"Azerbaijan","official_name":"Republic of Azerbaijan","flag":"🇦🇿","region":"Asia","subregion":"Western Asia","capital":"Baku","latlng":[40.5,47.5],"currency":{"code":"AZN","name":"Azerbaijani manat","symbol":"₼"},"dialing_code":"+9","tld":".az"},"BI":{"alpha2":"BI","alpha3":"BDI","name":"Burundi","official_name":"Republic of Burundi","flag":"🇧🇮","region":"Africa","subregion":"Eastern Africa","capital":"Gitega","latlng":[-3.5,30],"currency":{"code":"BIF","name":"Burundian franc","symbol":"Fr"},"dialing_code":"+2","tld":".bi"},"BE":{"alpha2":"BE","alpha3":"BEL","name":"Belgium","official_name":"Kingdom of Belgium","flag":"🇧🇪","region":"Europe","subregion":"Western Europe","capital":"Brussels","latlng":[50.83333333,4],"currency":{"code":"EUR","name":"Euro","symbol":"€"},"dialing_code":"+3","tld":".be"},"BJ":{"alpha2":"BJ","alpha3":"BEN","name":"Benin","official_name":"Republic of Benin","flag":"🇧🇯","region":"Africa","subregion":"Western Africa","capital":"Porto-Novo","latlng":[9.5,2.25],"currency":{"code":"XOF","name":"West African CFA franc","symbol":"Fr"},"dialing_code":"+2","tld":".bj"},"BF":{"alpha2":"BF","alpha3":"BFA","name":"Burkina Faso","official_name":"Burkina Faso","flag":"🇧🇫","region":"Africa","subregion":"Western Africa","capital":"Ouagadougou","latlng":[13,-2],"currency":{"code":"XOF","name":"West African CFA franc","symbol":"Fr"},"dialing_code":"+2","tld":".bf"},"BD":{"alpha2":"BD","alpha3":"BGD","name":"Bangladesh","official_name":"People's Republic of Bangladesh","flag":"🇧🇩","region":"Asia","subregion":"Southern Asia","capital":"Dhaka","latlng":[24,90],"currency":{"code":"BDT","name":"Bangladeshi taka","symbol":"৳"},"dialing_code":"+8","tld":".bd"},"BG":{"alpha2":"BG","alpha3":"BGR","name":"Bulgaria","official_name":"Republic of Bulgaria","flag":"🇧🇬","region":"Europe","subregion":"Southeast Europe","capital":"Sofia","latlng":[43,25],"currency":{"code":"BGN","name":"Bulgarian lev","symbol":"лв"},"dialing_code":"+3","tld":".bg"},"BH":{"alpha2":"BH","alpha3":"BHR","name":"Bahrain","official_name":"Kingdom of Bahrain","flag":"🇧🇭","region":"Asia","subregion":"Western Asia","capital":"Manama","latlng":[26,50.55],"currency":{"code":"BHD","name":"Bahraini dinar","symbol":".د.ب"},"dialing_code":"+9","tld":".bh"},"BS":{"alpha2":"BS","alpha3":"BHS","name":"Bahamas","official_name":"Commonwealth of the Bahamas","flag":"🇧🇸","region":"Americas","subregion":"Caribbean","capital":"Nassau","latlng":[24.25,-76],"currency":{"code":"BSD","name":"Bahamian dollar","symbol":"$"},"dialing_code":"+1","tld":".bs"},"BA":{"alpha2":"BA","alpha3":"BIH","name":"Bosnia and Herzegovina","official_name":"Bosnia and Herzegovina","flag":"🇧🇦","region":"Europe","subregion":"Southeast Europe","capital":"Sarajevo","latlng":[44,18],"currency":{"code":"BAM","name":"Bosnia and Herzegovina convertible mark","symbol":"KM"},"dialing_code":"+3","tld":".ba"},"BL":{"alpha2":"BL","alpha3":"BLM","name":"Saint Barthélemy","official_name":"Collectivity of Saint Barthélemy","flag":"🇧🇱","region":"Americas","subregion":"Caribbean","capital":"Gustavia","latlng":[18.5,-63.41666666],"currency":{"code":"EUR","name":"Euro","symbol":"€"},"dialing_code":"+5","tld":".bl"},"SH":{"alpha2":"SH","alpha3":"SHN","name":"Saint Helena, Ascension and Tristan da Cunha","official_name":"Saint Helena, Ascension and Tristan da Cunha","flag":"🇸🇭","region":"Africa","subregion":"Western Africa","capital":"Jamestown","latlng":[-15.95,-5.72],"currency":{"code":"GBP","name":"Pound sterling","symbol":"£"},"dialing_code":"+2","tld":".sh"},"BY":{"alpha2":"BY","alpha3":"BLR","name":"Belarus","official_name":"Republic of Belarus","flag":"🇧🇾","region":"Europe","subregion":"Eastern Europe","capital":"Minsk","latlng":[53,28],"currency":{"code":"BYN","name":"Belarusian ruble","symbol":"Br"},"dialing_code":"+3","tld":".by"},"BZ":{"alpha2":"BZ","alpha3":"BLZ","name":"Belize","official_name":"Belize","flag":"🇧🇿","region":"Americas","subregion":"Central America","capital":"Belmopan","latlng":[17.25,-88.75],"currency":{"code":"BZD","name":"Belize dollar","symbol":"$"},"dialing_code":"+5","tld":".bz"},"BM":{"alpha2":"BM","alpha3":"BMU","name":"Bermuda","official_name":"Bermuda","flag":"🇧🇲","region":"Americas","subregion":"North America","capital":"Hamilton","latlng":[32.33333333,-64.75],"currency":{"code":"BMD","name":"Bermudian dollar","symbol":"$"},"dialing_code":"+1","tld":".bm"},"BO":{"alpha2":"BO","alpha3":"BOL","name":"Bolivia","official_name":"Plurinational State of Bolivia","flag":"🇧🇴","region":"Americas","subregion":"South America","capital":"Sucre","latlng":[-17,-65],"currency":{"code":"BOB","name":"Bolivian boliviano","symbol":"Bs."},"dialing_code":"+5","tld":".bo"},"BQ":{"alpha2":"BQ","alpha3":"BES","name":"Caribbean Netherlands","official_name":"Bonaire, Sint Eustatius and Saba","flag":null,"region":"Americas","subregion":"Caribbean","capital":"Kralendijk","latlng":[12.18,-68.25],"currency":{"code":"USD","name":"United States dollar","symbol":"$"},"dialing_code":"+5","tld":".bq"},"BR":{"alpha2":"BR","alpha3":"BRA","name":"Brazil","official_name":"Federative Republic of Brazil","flag":"🇧🇷","region":"Americas","subregion":"South America","capital":"Brasília","latlng":[-10,-55],"currency":{"code":"BRL","name":"Brazilian real","symbol":"R$"},"dialing_code":"+5","tld":".br"},"BB":{"alpha2":"BB","alpha3":"BRB","name":"Barbados","official_name":"Barbados","flag":"🇧🇧","region":"Americas","subregion":"Caribbean","capital":"Bridgetown","latlng":[13.16666666,-59.53333333],"currency":{"code":"BBD","name":"Barbadian dollar","symbol":"$"},"dialing_code":"+1","tld":".bb"},"BN":{"alpha2":"BN","alpha3":"BRN","name":"Brunei","official_name":"Nation of Brunei, Abode of Peace","flag":"🇧🇳","region":"Asia","subregion":"South-Eastern Asia","capital":"Bandar Seri Begawan","latlng":[4.5,114.66666666],"currency":{"code":"BND","name":"Brunei dollar","symbol":"$"},"dialing_code":"+6","tld":".bn"},"BT":{"alpha2":"BT","alpha3":"BTN","name":"Bhutan","official_name":"Kingdom of Bhutan","flag":"🇧🇹","region":"Asia","subregion":"Southern Asia","capital":"Thimphu","latlng":[27.5,90.5],"currency":{"code":"BTN","name":"Bhutanese ngultrum","symbol":"Nu."},"dialing_code":"+9","tld":".bt"},"BV":{"alpha2":"BV","alpha3":"BVT","name":"Bouvet Island","official_name":"Bouvet Island","flag":"🇧🇻","region":"Antarctic","subregion":null,"capital":null,"latlng":[-54.43333333,3.4],"currency":null,"dialing_code":"+4","tld":".bv"},"BW":{"alpha2":"BW","alpha3":"BWA","name":"Botswana","official_name":"Republic of Botswana","flag":"🇧🇼","region":"Africa","subregion":"Southern Africa","capital":"Gaborone","latlng":[-22,24],"currency":{"code":"BWP","name":"Botswana pula","symbol":"P"},"dialing_code":"+2","tld":".bw"},"CF":{"alpha2":"CF","alpha3":"CAF","name":"Central African Republic","official_name":"Central African Republic","flag":"🇨🇫","region":"Africa","subregion":"Middle Africa","capital":"Bangui","latlng":[7,21],"currency":{"code":"XAF","name":"Central African CFA franc","symbol":"Fr"},"dialing_code":"+2","tld":".cf"},"CA":{"alpha2":"CA","alpha3":"CAN","name":"Canada","official_name":"Canada","flag":"🇨🇦","region":"Americas","subregion":"North America","capital":"Ottawa","latlng":[60,-95],"currency":{"code":"CAD","name":"Canadian dollar","symbol":"$"},"dialing_code":"+1","tld":".ca"},"CC":{"alpha2":"CC","alpha3":"CCK","name":"Cocos (Keeling) Islands","official_name":"Territory of the Cocos (Keeling) Islands","flag":"🇨🇨","region":"Oceania","subregion":"Australia and New Zealand","capital":"West Island","latlng":[-12.5,96.83333333],"currency":{"code":"AUD","name":"Australian dollar","symbol":"$"},"dialing_code":"+6","tld":".cc"},"CH":{"alpha2":"CH","alpha3":"CHE","name":"Switzerland","official_name":"Swiss Confederation","flag":"🇨🇭","region":"Europe","subregion":"Western Europe","capital":"Bern","latlng":[47,8],"currency":{"code":"CHF","name":"Swiss franc","symbol":"Fr."},"dialing_code":"+4","tld":".ch"},"CL":{"alpha2":"CL","alpha3":"CHL","name":"Chile","official_name":"Republic of Chile","flag":"🇨🇱","region":"Americas","subregion":"South America","capital":"Santiago","latlng":[-30,-71],"currency":{"code":"CLP","name":"Chilean peso","symbol":"$"},"dialing_code":"+5","tld":".cl"},"CN":{"alpha2":"CN","alpha3":"CHN","name":"China","official_name":"People's Republic of China","flag":"🇨🇳","region":"Asia","subregion":"Eastern Asia","capital":"Beijing","latlng":[35,105],"currency":{"code":"CNY","name":"Chinese yuan","symbol":"¥"},"dialing_code":"+8","tld":".cn"},"CI":{"alpha2":"CI","alpha3":"CIV","name":"Ivory Coast","official_name":"Republic of Côte d'Ivoire","flag":"🇨🇮","region":"Africa","subregion":"Western Africa","capital":"Yamoussoukro","latlng":[8,-5],"currency":{"code":"XOF","name":"West African CFA franc","symbol":"Fr"},"dialing_code":"+2","tld":".ci"},"CM":{"alpha2":"CM","alpha3":"CMR","name":"Cameroon","official_name":"Republic of Cameroon","flag":"🇨🇲","region":"Africa","subregion":"Middle Africa","capital":"Yaoundé","latlng":[6,12],"currency":{"code":"XAF","name":"Central African CFA franc","symbol":"Fr"},"dialing_code":"+2","tld":".cm"},"CD":{"alpha2":"CD","alpha3":"COD","name":"DR Congo","official_name":"Democratic Republic of the Congo","flag":"🇨🇩","region":"Africa","subregion":"Middle Africa","capital":"Kinshasa","latlng":[0,25],"currency":{"code":"CDF","name":"Congolese franc","symbol":"FC"},"dialing_code":"+2","tld":".cd"},"CG":{"alpha2":"CG","alpha3":"COG","name":"Congo","official_name":"Republic of the Congo","flag":"🇨🇬","region":"Africa","subregion":"Middle Africa","capital":"Brazzaville","latlng":[-1,15],"currency":{"code":"XAF","name":"Central African CFA franc","symbol":"Fr"},"dialing_code":"+2","tld":".cg"},"CK":{"alpha2":"CK","alpha3":"COK","name":"Cook Islands","official_name":"Cook Islands","flag":"🇨🇰","region":"Oceania","subregion":"Polynesia","capital":"Avarua","latlng":[-21.23333333,-159.76666666],"currency":{"code":"CKD","name":"Cook Islands dollar","symbol":"$"},"dialing_code":"+6","tld":".ck"},"CO":{"alpha2":"CO","alpha3":"COL","name":"Colombia","official_name":"Republic of Colombia","flag":"🇨🇴","region":"Americas","subregion":"South America","capital":"Bogotá","latlng":[4,-72],"currency":{"code":"COP","name":"Colombian peso","symbol":"$"},"dialing_code":"+5","tld":".co"},"KM":{"alpha2":"KM","alpha3":"COM","name":"Comoros","official_name":"Union of the Comoros","flag":"🇰🇲","region":"Africa","subregion":"Eastern Africa","capital":"Moroni","latlng":[-12.16666666,44.25],"currency":{"code":"KMF","name":"Comorian franc","symbol":"Fr"},"dialing_code":"+2","tld":".km"},"CV":{"alpha2":"CV","alpha3":"CPV","name":"Cape Verde","official_name":"Republic of Cabo Verde","flag":"🇨🇻","region":"Africa","subregion":"Western Africa","capital":"Praia","latlng":[16,-24],"currency":{"code":"CVE","name":"Cape Verdean escudo","symbol":"Esc"},"dialing_code":"+2","tld":".cv"},"CR":{"alpha2":"CR","alpha3":"CRI","name":"Costa Rica","official_name":"Republic of Costa Rica","flag":"🇨🇷","region":"Americas","subregion":"Central America","capital":"San José","latlng":[10,-84],"currency":{"code":"CRC","name":"Costa Rican colón","symbol":"₡"},"dialing_code":"+5","tld":".cr"},"CU":{"alpha2":"CU","alpha3":"CUB","name":"Cuba","official_name":"Republic of Cuba","flag":"🇨🇺","region":"Americas","subregion":"Caribbean","capital":"Havana","latlng":[21.5,-80],"currency":{"code":"CUC","name":"Cuban convertible peso","symbol":"$"},"dialing_code":"+5","tld":".cu"},"CW":{"alpha2":"CW","alpha3":"CUW","name":"Curaçao","official_name":"Country of Curaçao","flag":"🇨🇼","region":"Americas","subregion":"Caribbean","capital":"Willemstad","latlng":[12.116667,-68.933333],"currency":{"code":"ANG","name":"Netherlands Antillean guilder","symbol":"ƒ"},"dialing_code":"+5","tld":".cw"},"CX":{"alpha2":"CX","alpha3":"CXR","name":"Christmas Island","official_name":"Territory of Christmas Island","flag":"🇨🇽","region":"Oceania","subregion":"Australia and New Zealand","capital":"Flying Fish Cove","latlng":[-10.5,105.66666666],"currency":{"code":"AUD","name":"Australian dollar","symbol":"$"},"dialing_code":"+6","tld":".cx"},"KY":{"alpha2":"KY","alpha3":"CYM","name":"Cayman Islands","official_name":"Cayman Islands","flag":"🇰🇾","region":"Americas","subregion":"Caribbean","capital":"George Town","latlng":[19.5,-80.5],"currency":{"code":"KYD","name":"Cayman Islands dollar","symbol":"$"},"dialing_code":"+1","tld":".ky"},"CY":{"alpha2":"CY","alpha3":"CYP","name":"Cyprus","official_name":"Republic of Cyprus","flag":"🇨🇾","region":"Europe","subregion":"Southern Europe","capital":"Nicosia","latlng":[35,33],"currency":{"code":"EUR","name":"Euro","symbol":"€"},"dialing_code":"+3","tld":".cy"},"CZ":{"alpha2":"CZ","alpha3":"CZE","name":"Czechia","official_name":"Czech Republic","flag":"🇨🇿","region":"Europe","subregion":"Central Europe","capital":"Prague","latlng":[49.75,15.5],"currency":{"code":"CZK","name":"Czech koruna","symbol":"Kč"},"dialing_code":"+4","tld":".cz"},"DE":{"alpha2":"DE","alpha3":"DEU","name":"Germany","official_name":"Federal Republic of Germany","flag":"🇩🇪","region":"Europe","subregion":"Western Europe","capital":"Berlin","latlng":[51,9],"currency":{"code":"EUR","name":"Euro","symbol":"€"},"dialing_code":"+4","tld":".de"},"DJ":{"alpha2":"DJ","alpha3":"DJI","name":"Djibouti","official_name":"Republic of Djibouti","flag":"🇩🇯","region":"Africa","subregion":"Eastern Africa","capital":"Djibouti","latlng":[11.5,43],"currency":{"code":"DJF","name":"Djiboutian franc","symbol":"Fr"},"dialing_code":"+2","tld":".dj"},"DM":{"alpha2":"DM","alpha3":"DMA","name":"Dominica","official_name":"Commonwealth of Dominica","flag":"🇩🇲","region":"Americas","subregion":"Caribbean","capital":"Roseau","latlng":[15.41666666,-61.33333333],"currency":{"code":"XCD","name":"Eastern Caribbean dollar","symbol":"$"},"dialing_code":"+1","tld":".dm"},"DK":{"alpha2":"DK","alpha3":"DNK","name":"Denmark","official_name":"Kingdom of Denmark","flag":"🇩🇰","region":"Europe","subregion":"Northern Europe","capital":"Copenhagen","latlng":[56,10],"currency":{"code":"DKK","name":"Danish krone","symbol":"kr"},"dialing_code":"+4","tld":".dk"},"DO":{"alpha2":"DO","alpha3":"DOM","name":"Dominican Republic","official_name":"Dominican Republic","flag":"🇩🇴","region":"Americas","subregion":"Caribbean","capital":"Santo Domingo","latlng":[19,-70.66666666],"currency":{"code":"DOP","name":"Dominican peso","symbol":"$"},"dialing_code":"+1","tld":".do"},"DZ":{"alpha2":"DZ","alpha3":"DZA","name":"Algeria","official_name":"People's Democratic Republic of Algeria","flag":"🇩🇿","region":"Africa","subregion":"Northern Africa","capital":"Algiers","latlng":[28,3],"currency":{"code":"DZD","name":"Algerian dinar","symbol":"د.ج"},"dialing_code":"+2","tld":".dz"},"EC":{"alpha2":"EC","alpha3":"ECU","name":"Ecuador","official_name":"Republic of Ecuador","flag":"🇪🇨","region":"Americas","subregion":"South America","capital":"Quito","latlng":[-2,-77.5],"currency":{"code":"USD","name":"United States dollar","symbol":"$"},"dialing_code":"+5","tld":".ec"},"EG":{"alpha2":"EG","alpha3":"EGY","name":"Egypt","official_name":"Arab Republic of Egypt","flag":"🇪🇬","region":"Africa","subregion":"Northern Africa","capital":"Cairo","latlng":[27,30],"currency":{"code":"EGP","name":"Egyptian pound","symbol":"£"},"dialing_code":"+2","tld":".eg"},"ER":{"alpha2":"ER","alpha3":"ERI","name":"Eritrea","official_name":"State of Eritrea","flag":"🇪🇷","region":"Africa","subregion":"Eastern Africa","capital":"Asmara","latlng":[15,39],"currency":{"code":"ERN","name":"Eritrean nakfa","symbol":"Nfk"},"dialing_code":"+2","tld":".er"},"EH":{"alpha2":"EH","alpha3":"ESH","name":"Western Sahara","official_name":"Sahrawi Arab Democratic Republic","flag":"🇪🇭","region":"Africa","subregion":"Northern Africa","capital":"El Aaiún","latlng":[24.5,-13],"currency":{"code":"DZD","name":"Algerian dinar","symbol":"دج"},"dialing_code":"+2","tld":".eh"},"ES":{"alpha2":"ES","alpha3":"ESP","name":"Spain","official_name":"Kingdom of Spain","flag":"🇪🇸","region":"Europe","subregion":"Southern Europe","capital":"Madrid","latlng":[40,-4],"currency":{"code":"EUR","name":"Euro","symbol":"€"},"dialing_code":"+3","tld":".es"},"EE":{"alpha2":"EE","alpha3":"EST","name":"Estonia","official_name":"Republic of Estonia","flag":"🇪🇪","region":"Europe","subregion":"Northern Europe","capital":"Tallinn","latlng":[59,26],"currency":{"code":"EUR","name":"Euro","symbol":"€"},"dialing_code":"+3","tld":".ee"},"ET":{"alpha2":"ET","alpha3":"ETH","name":"Ethiopia","official_name":"Federal Democratic Republic of Ethiopia","flag":"🇪🇹","region":"Africa","subregion":"Eastern Africa","capital":"Addis Ababa","latlng":[8,38],"currency":{"code":"ETB","name":"Ethiopian birr","symbol":"Br"},"dialing_code":"+2","tld":".et"},"FI":{"alpha2":"FI","alpha3":"FIN","name":"Finland","official_name":"Republic of Finland","flag":"🇫🇮","region":"Europe","subregion":"Northern Europe","capital":"Helsinki","latlng":[64,26],"currency":{"code":"EUR","name":"Euro","symbol":"€"},"dialing_code":"+3","tld":".fi"},"FJ":{"alpha2":"FJ","alpha3":"FJI","name":"Fiji","official_name":"Republic of Fiji","flag":"🇫🇯","region":"Oceania","subregion":"Melanesia","capital":"Suva","latlng":[-18,175],"currency":{"code":"FJD","name":"Fijian dollar","symbol":"$"},"dialing_code":"+6","tld":".fj"},"FK":{"alpha2":"FK","alpha3":"FLK","name":"Falkland Islands","official_name":"Falkland Islands","flag":"🇫🇰","region":"Americas","subregion":"South America","capital":"Stanley","latlng":[-51.75,-59],"currency":{"code":"FKP","name":"Falkland Islands pound","symbol":"£"},"dialing_code":"+5","tld":".fk"},"FR":{"alpha2":"FR","alpha3":"FRA","name":"France","official_name":"French Republic","flag":"🇫🇷","region":"Europe","subregion":"Western Europe","capital":"Paris","latlng":[46,2],"currency":{"code":"EUR","name":"Euro","symbol":"€"},"dialing_code":"+3","tld":".fr"},"FO":{"alpha2":"FO","alpha3":"FRO","name":"Faroe Islands","official_name":"Faroe Islands","flag":"🇫🇴","region":"Europe","subregion":"Northern Europe","capital":"Tórshavn","latlng":[62,-7],"currency":{"code":"DKK","name":"Danish krone","symbol":"kr"},"dialing_code":"+2","tld":".fo"},"FM":{"alpha2":"FM","alpha3":"FSM","name":"Micronesia","official_name":"Federated States of Micronesia","flag":"🇫🇲","region":"Oceania","subregion":"Micronesia","capital":"Palikir","latlng":[6.91666666,158.25],"currency":null,"dialing_code":"+6","tld":".fm"},"GA":{"alpha2":"GA","alpha3":"GAB","name":"Gabon","official_name":"Gabonese Republic","flag":"🇬🇦","region":"Africa","subregion":"Middle Africa","capital":"Libreville","latlng":[-1,11.75],"currency":{"code":"XAF","name":"Central African CFA franc","symbol":"Fr"},"dialing_code":"+2","tld":".ga"},"GB":{"alpha2":"GB","alpha3":"GBR","name":"United Kingdom","official_name":"United Kingdom of Great Britain and Northern Ireland","flag":"🇬🇧","region":"Europe","subregion":"Northern Europe","capital":"London","latlng":[54,-2],"currency":{"code":"GBP","name":"British pound","symbol":"£"},"dialing_code":"+4","tld":".uk"},"GE":{"alpha2":"GE","alpha3":"GEO","name":"Georgia","official_name":"Georgia","flag":"🇬🇪","region":"Asia","subregion":"Western Asia","capital":"Tbilisi","latlng":[42,43.5],"currency":{"code":"GEL","name":"lari","symbol":"₾"},"dialing_code":"+9","tld":".ge"},"GG":{"alpha2":"GG","alpha3":"GGY","name":"Guernsey","official_name":"Bailiwick of Guernsey","flag":"🇬🇬","region":"Europe","subregion":"Northern Europe","capital":"St. Peter Port","latlng":[49.46666666,-2.58333333],"currency":{"code":"GBP","name":"British pound","symbol":"£"},"dialing_code":"+4","tld":".gg"},"GH":{"alpha2":"GH","alpha3":"GHA","name":"Ghana","official_name":"Republic of Ghana","flag":"🇬🇭","region":"Africa","subregion":"Western Africa","capital":"Accra","latlng":[8,-2],"currency":{"code":"GHS","name":"Ghanaian cedi","symbol":"₵"},"dialing_code":"+2","tld":".gh"},"GI":{"alpha2":"GI","alpha3":"GIB","name":"Gibraltar","official_name":"Gibraltar","flag":"🇬🇮","region":"Europe","subregion":"Southern Europe","capital":"Gibraltar","latlng":[36.13333333,-5.35],"currency":{"code":"GIP","name":"Gibraltar pound","symbol":"£"},"dialing_code":"+3","tld":".gi"},"GN":{"alpha2":"GN","alpha3":"GIN","name":"Guinea","official_name":"Republic of Guinea","flag":"🇬🇳","region":"Africa","subregion":"Western Africa","capital":"Conakry","latlng":[11,-10],"currency":{"code":"GNF","name":"Guinean franc","symbol":"Fr"},"dialing_code":"+2","tld":".gn"},"GP":{"alpha2":"GP","alpha3":"GLP","name":"Guadeloupe","official_name":"Guadeloupe","flag":"🇬🇵","region":"Americas","subregion":"Caribbean","capital":"Basse-Terre","latlng":[16.25,-61.583333],"currency":{"code":"EUR","name":"Euro","symbol":"€"},"dialing_code":"+5","tld":".gp"},"GM":{"alpha2":"GM","alpha3":"GMB","name":"Gambia","official_name":"Republic of the Gambia","flag":"🇬🇲","region":"Africa","subregion":"Western Africa","capital":"Banjul","latlng":[13.46666666,-16.56666666],"currency":{"code":"GMD","name":"dalasi","symbol":"D"},"dialing_code":"+2","tld":".gm"},"GW":{"alpha2":"GW","alpha3":"GNB","name":"Guinea-Bissau","official_name":"Republic of Guinea-Bissau","flag":"🇬🇼","region":"Africa","subregion":"Western Africa","capital":"Bissau","latlng":[12,-15],"currency":{"code":"XOF","name":"West African CFA franc","symbol":"Fr"},"dialing_code":"+2","tld":".gw"},"GQ":{"alpha2":"GQ","alpha3":"GNQ","name":"Equatorial Guinea","official_name":"Republic of Equatorial Guinea","flag":"🇬🇶","region":"Africa","subregion":"Middle Africa","capital":"Malabo","latlng":[2,10],"currency":{"code":"XAF","name":"Central African CFA franc","symbol":"Fr"},"dialing_code":"+2","tld":".gq"},"GR":{"alpha2":"GR","alpha3":"GRC","name":"Greece","official_name":"Hellenic Republic","flag":"🇬🇷","region":"Europe","subregion":"Southern Europe","capital":"Athens","latlng":[39,22],"currency":{"code":"EUR","name":"Euro","symbol":"€"},"dialing_code":"+3","tld":".gr"},"GD":{"alpha2":"GD","alpha3":"GRD","name":"Grenada","official_name":"Grenada","flag":"🇬🇩","region":"Americas","subregion":"Caribbean","capital":"St. George's","latlng":[12.11666666,-61.66666666],"currency":{"code":"XCD","name":"Eastern Caribbean dollar","symbol":"$"},"dialing_code":"+1","tld":".gd"},"GL":{"alpha2":"GL","alpha3":"GRL","name":"Greenland","official_name":"Greenland","flag":"🇬🇱","region":"Americas","subregion":"North America","capital":"Nuuk","latlng":[72,-40],"currency":{"code":"DKK","name":"krone","symbol":"kr."},"dialing_code":"+2","tld":".gl"},"GT":{"alpha2":"GT","alpha3":"GTM","name":"Guatemala","official_name":"Republic of Guatemala","flag":"🇬🇹","region":"Americas","subregion":"Central America","capital":"Guatemala City","latlng":[15.5,-90.25],"currency":{"code":"GTQ","name":"Guatemalan quetzal","symbol":"Q"},"dialing_code":"+5","tld":".gt"},"GF":{"alpha2":"GF","alpha3":"GUF","name":"French Guiana","official_name":"Guiana","flag":"🇬🇫","region":"Americas","subregion":"South America","capital":"Cayenne","latlng":[4,-53],"currency":{"code":"EUR","name":"Euro","symbol":"€"},"dialing_code":"+5","tld":".gf"},"GU":{"alpha2":"GU","alpha3":"GUM","name":"Guam","official_name":"Guam","flag":"🇬🇺","region":"Oceania","subregion":"Micronesia","capital":"Hagåtña","latlng":[13.46666666,144.78333333],"currency":{"code":"USD","name":"United States dollar","symbol":"$"},"dialing_code":"+1","tld":".gu"},"GY":{"alpha2":"GY","alpha3":"GUY","name":"Guyana","official_name":"Co-operative Republic of Guyana","flag":"🇬🇾","region":"Americas","subregion":"South America","capital":"Georgetown","latlng":[5,-59],"currency":{"code":"GYD","name":"Guyanese dollar","symbol":"$"},"dialing_code":"+5","tld":".gy"},"HK":{"alpha2":"HK","alpha3":"HKG","name":"Hong Kong","official_name":"Hong Kong Special Administrative Region of the People's Republic of China","flag":"🇭🇰","region":"Asia","subregion":"Eastern Asia","capital":"City of Victoria","latlng":[22.267,114.188],"currency":{"code":"HKD","name":"Hong Kong dollar","symbol":"$"},"dialing_code":"+8","tld":".hk"},"HM":{"alpha2":"HM","alpha3":"HMD","name":"Heard Island and McDonald Islands","official_name":"Heard Island and McDonald Islands","flag":"🇭🇲","region":"Antarctic","subregion":null,"capital":null,"latlng":[-53.1,72.51666666],"currency":null,"dialing_code":null,"tld":".hm"},"HN":{"alpha2":"HN","alpha3":"HND","name":"Honduras","official_name":"Republic of Honduras","flag":"🇭🇳","region":"Americas","subregion":"Central America","capital":"Tegucigalpa","latlng":[15,-86.5],"currency":{"code":"HNL","name":"Honduran lempira","symbol":"L"},"dialing_code":"+5","tld":".hn"},"HR":{"alpha2":"HR","alpha3":"HRV","name":"Croatia","official_name":"Republic of Croatia","flag":"🇭🇷","region":"Europe","subregion":"Southeast Europe","capital":"Zagreb","latlng":[45.16666666,15.5],"currency":{"code":"EUR","name":"Euro","symbol":"€"},"dialing_code":"+3","tld":".hr"},"HT":{"alpha2":"HT","alpha3":"HTI","name":"Haiti","official_name":"Republic of Haiti","flag":"🇭🇹","region":"Americas","subregion":"Caribbean","capital":"Port-au-Prince","latlng":[19,-72.41666666],"currency":{"code":"HTG","name":"Haitian gourde","symbol":"G"},"dialing_code":"+5","tld":".ht"},"HU":{"alpha2":"HU","alpha3":"HUN","name":"Hungary","official_name":"Hungary","flag":"🇭🇺","region":"Europe","subregion":"Central Europe","capital":"Budapest","latlng":[47,20],"currency":{"code":"HUF","name":"Hungarian forint","symbol":"Ft"},"dialing_code":"+3","tld":".hu"},"ID":{"alpha2":"ID","alpha3":"IDN","name":"Indonesia","official_name":"Republic of Indonesia","flag":"🇮🇩","region":"Asia","subregion":"South-Eastern Asia","capital":"Jakarta","latlng":[-5,120],"currency":{"code":"IDR","name":"Indonesian rupiah","symbol":"Rp"},"dialing_code":"+6","tld":".id"},"IM":{"alpha2":"IM","alpha3":"IMN","name":"Isle of Man","official_name":"Isle of Man","flag":"🇮🇲","region":"Europe","subregion":"Northern Europe","capital":"Douglas","latlng":[54.25,-4.5],"currency":{"code":"GBP","name":"British pound","symbol":"£"},"dialing_code":"+4","tld":".im"},"IN":{"alpha2":"IN","alpha3":"IND","name":"India","official_name":"Republic of India","flag":"🇮🇳","region":"Asia","subregion":"Southern Asia","capital":"New Delhi","latlng":[20,77],"currency":{"code":"INR","name":"Indian rupee","symbol":"₹"},"dialing_code":"+9","tld":".in"},"IO":{"alpha2":"IO","alpha3":"IOT","name":"British Indian Ocean Territory","official_name":"British Indian Ocean Territory","flag":"🇮🇴","region":"Africa","subregion":"Eastern Africa","capital":"Diego Garcia","latlng":[-6,71.5],"currency":{"code":"USD","name":"United States dollar","symbol":"$"},"dialing_code":"+2","tld":".io"},"IE":{"alpha2":"IE","alpha3":"IRL","name":"Ireland","official_name":"Republic of Ireland","flag":"🇮🇪","region":"Europe","subregion":"Northern Europe","capital":"Dublin","latlng":[53,-8],"currency":{"code":"EUR","name":"Euro","symbol":"€"},"dialing_code":"+3","tld":".ie"},"IR":{"alpha2":"IR","alpha3":"IRN","name":"Iran","official_name":"Islamic Republic of Iran","flag":"🇮🇷","region":"Asia","subregion":"Southern Asia","capital":"Tehran","latlng":[32,53],"currency":{"code":"IRR","name":"Iranian rial","symbol":"﷼"},"dialing_code":"+9","tld":".ir"},"IQ":{"alpha2":"IQ","alpha3":"IRQ","name":"Iraq","official_name":"Republic of Iraq","flag":"🇮🇶","region":"Asia","subregion":"Western Asia","capital":"Baghdad","latlng":[33,44],"currency":{"code":"IQD","name":"Iraqi dinar","symbol":"ع.د"},"dialing_code":"+9","tld":".iq"},"IS":{"alpha2":"IS","alpha3":"ISL","name":"Iceland","official_name":"Iceland","flag":"🇮🇸","region":"Europe","subregion":"Northern Europe","capital":"Reykjavik","latlng":[65,-18],"currency":{"code":"ISK","name":"Icelandic króna","symbol":"kr"},"dialing_code":"+3","tld":".is"},"IL":{"alpha2":"IL","alpha3":"ISR","name":"Israel","official_name":"State of Israel","flag":"🇮🇱","region":"Asia","subregion":"Western Asia","capital":"Jerusalem","latlng":[31.47,35.13],"currency":{"code":"ILS","name":"Israeli new shekel","symbol":"₪"},"dialing_code":"+9","tld":".il"},"IT":{"alpha2":"IT","alpha3":"ITA","name":"Italy","official_name":"Italian Republic","flag":"🇮🇹","region":"Europe","subregion":"Southern Europe","capital":"Rome","latlng":[42.83333333,12.83333333],"currency":{"code":"EUR","name":"Euro","symbol":"€"},"dialing_code":"+3","tld":".it"},"JM":{"alpha2":"JM","alpha3":"JAM","name":"Jamaica","official_name":"Jamaica","flag":"🇯🇲","region":"Americas","subregion":"Caribbean","capital":"Kingston","latlng":[18.25,-77.5],"currency":{"code":"JMD","name":"Jamaican dollar","symbol":"$"},"dialing_code":"+1","tld":".jm"},"JE":{"alpha2":"JE","alpha3":"JEY","name":"Jersey","official_name":"Bailiwick of Jersey","flag":"🇯🇪","region":"Europe","subregion":"Northern Europe","capital":"Saint Helier","latlng":[49.25,-2.16666666],"currency":{"code":"GBP","name":"British pound","symbol":"£"},"dialing_code":"+4","tld":".je"},"JO":{"alpha2":"JO","alpha3":"JOR","name":"Jordan","official_name":"Hashemite Kingdom of Jordan","flag":"🇯🇴","region":"Asia","subregion":"Western Asia","capital":"Amman","latlng":[31,36],"currency":{"code":"JOD","name":"Jordanian dinar","symbol":"د.ا"},"dialing_code":"+9","tld":".jo"},"JP":{"alpha2":"JP","alpha3":"JPN","name":"Japan","official_name":"Japan","flag":"🇯🇵","region":"Asia","subregion":"Eastern Asia","capital":"Tokyo","latlng":[36,138],"currency":{"code":"JPY","name":"Japanese yen","symbol":"¥"},"dialing_code":"+8","tld":".jp"},"KZ":{"alpha2":"KZ","alpha3":"KAZ","name":"Kazakhstan","official_name":"Republic of Kazakhstan","flag":"🇰🇿","region":"Asia","subregion":"Central Asia","capital":"Astana","latlng":[48,68],"currency":{"code":"KZT","name":"Kazakhstani tenge","symbol":"₸"},"dialing_code":"+7","tld":".kz"},"KE":{"alpha2":"KE","alpha3":"KEN","name":"Kenya","official_name":"Republic of Kenya","flag":"🇰🇪","region":"Africa","subregion":"Eastern Africa","capital":"Nairobi","latlng":[1,38],"currency":{"code":"KES","name":"Kenyan shilling","symbol":"Sh"},"dialing_code":"+2","tld":".ke"},"KG":{"alpha2":"KG","alpha3":"KGZ","name":"Kyrgyzstan","official_name":"Kyrgyz Republic","flag":"🇰🇬","region":"Asia","subregion":"Central Asia","capital":"Bishkek","latlng":[41,75],"currency":{"code":"KGS","name":"Kyrgyzstani som","symbol":"с"},"dialing_code":"+9","tld":".kg"},"KH":{"alpha2":"KH","alpha3":"KHM","name":"Cambodia","official_name":"Kingdom of Cambodia","flag":"🇰🇭","region":"Asia","subregion":"South-Eastern Asia","capital":"Phnom Penh","latlng":[13,105],"currency":{"code":"KHR","name":"Cambodian riel","symbol":"៛"},"dialing_code":"+8","tld":".kh"},"KI":{"alpha2":"KI","alpha3":"KIR","name":"Kiribati","official_name":"Independent and Sovereign Republic of Kiribati","flag":"🇰🇮","region":"Oceania","subregion":"Micronesia","capital":"South Tarawa","latlng":[1.41666666,173],"currency":{"code":"AUD","name":"Australian dollar","symbol":"$"},"dialing_code":"+6","tld":".ki"},"KN":{"alpha2":"KN","alpha3":"KNA","name":"Saint Kitts and Nevis","official_name":"Federation of Saint Christopher and Nevis","flag":"🇰🇳","region":"Americas","subregion":"Caribbean","capital":"Basseterre","latlng":[17.33333333,-62.75],"currency":{"code":"XCD","name":"Eastern Caribbean dollar","symbol":"$"},"dialing_code":"+1","tld":".kn"},"KR":{"alpha2":"KR","alpha3":"KOR","name":"South Korea","official_name":"Republic of Korea","flag":"🇰🇷","region":"Asia","subregion":"Eastern Asia","capital":"Seoul","latlng":[37,127.5],"currency":{"code":"KRW","name":"South Korean won","symbol":"₩"},"dialing_code":"+8","tld":".kr"},"XK":{"alpha2":"XK","alpha3":"UNK","name":"Kosovo","official_name":"Republic of Kosovo","flag":"🇽🇰","region":"Europe","subregion":"Southeast Europe","capital":"Pristina","latlng":[42.666667,21.166667],"currency":{"code":"EUR","name":"Euro","symbol":"€"},"dialing_code":"+3","tld":".xk"},"KW":{"alpha2":"KW","alpha3":"KWT","name":"Kuwait","official_name":"State of Kuwait","flag":"🇰🇼","region":"Asia","subregion":"Western Asia","capital":"Kuwait City","latlng":[29.5,45.75],"currency":{"code":"KWD","name":"Kuwaiti dinar","symbol":"د.ك"},"dialing_code":"+9","tld":".kw"},"LA":{"alpha2":"LA","alpha3":"LAO","name":"Laos","official_name":"Lao People's Democratic Republic","flag":"🇱🇦","region":"Asia","subregion":"South-Eastern Asia","capital":"Vientiane","latlng":[18,105],"currency":{"code":"LAK","name":"Lao kip","symbol":"₭"},"dialing_code":"+8","tld":".la"},"LB":{"alpha2":"LB","alpha3":"LBN","name":"Lebanon","official_name":"Lebanese Republic","flag":"🇱🇧","region":"Asia","subregion":"Western Asia","capital":"Beirut","latlng":[33.83333333,35.83333333],"currency":{"code":"LBP","name":"Lebanese pound","symbol":"ل.ل"},"dialing_code":"+9","tld":".lb"},"LR":{"alpha2":"LR","alpha3":"LBR","name":"Liberia","official_name":"Republic of Liberia","flag":"🇱🇷","region":"Africa","subregion":"Western Africa","capital":"Monrovia","latlng":[6.5,-9.5],"currency":{"code":"LRD","name":"Liberian dollar","symbol":"$"},"dialing_code":"+2","tld":".lr"},"LY":{"alpha2":"LY","alpha3":"LBY","name":"Libya","official_name":"State of Libya","flag":"🇱🇾","region":"Africa","subregion":"Northern Africa","capital":"Tripoli","latlng":[25,17],"currency":{"code":"LYD","name":"Libyan dinar","symbol":"ل.د"},"dialing_code":"+2","tld":".ly"},"LC":{"alpha2":"LC","alpha3":"LCA","name":"Saint Lucia","official_name":"Saint Lucia","flag":"🇱🇨","region":"Americas","subregion":"Caribbean","capital":"Castries","latlng":[13.88333333,-60.96666666],"currency":{"code":"XCD","name":"Eastern Caribbean dollar","symbol":"$"},"dialing_code":"+1","tld":".lc"},"LI":{"alpha2":"LI","alpha3":"LIE","name":"Liechtenstein","official_name":"Principality of Liechtenstein","flag":"🇱🇮","region":"Europe","subregion":"Western Europe","capital":"Vaduz","latlng":[47.26666666,9.53333333],"currency":{"code":"CHF","name":"Swiss franc","symbol":"Fr"},"dialing_code":"+4","tld":".li"},"LK":{"alpha2":"LK","alpha3":"LKA","name":"Sri Lanka","official_name":"Democratic Socialist Republic of Sri Lanka","flag":"🇱🇰","region":"Asia","subregion":"Southern Asia","capital":"Colombo","latlng":[7,81],"currency":{"code":"LKR","name":"Sri Lankan rupee","symbol":"Rs රු"},"dialing_code":"+9","tld":".lk"},"LS":{"alpha2":"LS","alpha3":"LSO","name":"Lesotho","official_name":"Kingdom of Lesotho","flag":"🇱🇸","region":"Africa","subregion":"Southern Africa","capital":"Maseru","latlng":[-29.5,28.5],"currency":{"code":"LSL","name":"Lesotho loti","symbol":"L"},"dialing_code":"+2","tld":".ls"},"LT":{"alpha2":"LT","alpha3":"LTU","name":"Lithuania","official_name":"Republic of Lithuania","flag":"🇱🇹","region":"Europe","subregion":"Northern Europe","capital":"Vilnius","latlng":[56,24],"currency":{"code":"EUR","name":"Euro","symbol":"€"},"dialing_code":"+3","tld":".lt"},"LU":{"alpha2":"LU","alpha3":"LUX","name":"Luxembourg","official_name":"Grand Duchy of Luxembourg","flag":"🇱🇺","region":"Europe","subregion":"Western Europe","capital":"Luxembourg","latlng":[49.75,6.16666666],"currency":{"code":"EUR","name":"Euro","symbol":"€"},"dialing_code":"+3","tld":".lu"},"LV":{"alpha2":"LV","alpha3":"LVA","name":"Latvia","official_name":"Republic of Latvia","flag":"🇱🇻","region":"Europe","subregion":"Northern Europe","capital":"Riga","latlng":[57,25],"currency":{"code":"EUR","name":"Euro","symbol":"€"},"dialing_code":"+3","tld":".lv"},"MO":{"alpha2":"MO","alpha3":"MAC","name":"Macau","official_name":"Macao Special Administrative Region of the People's Republic of China","flag":"🇲🇴","region":"Asia","subregion":"Eastern Asia","capital":null,"latlng":[22.16666666,113.55],"currency":{"code":"MOP","name":"Macanese pataca","symbol":"P"},"dialing_code":"+8","tld":".mo"},"MF":{"alpha2":"MF","alpha3":"MAF","name":"Saint Martin","official_name":"Saint Martin","flag":"🇲🇫","region":"Americas","subregion":"Caribbean","capital":"Marigot","latlng":[18.08333333,-63.95],"currency":{"code":"EUR","name":"Euro","symbol":"€"},"dialing_code":"+5","tld":".fr"},"MA":{"alpha2":"MA","alpha3":"MAR","name":"Morocco","official_name":"Kingdom of Morocco","flag":"🇲🇦","region":"Africa","subregion":"Northern Africa","capital":"Rabat","latlng":[32,-5],"currency":{"code":"MAD","name":"Moroccan dirham","symbol":"د.م."},"dialing_code":"+2","tld":".ma"},"MC":{"alpha2":"MC","alpha3":"MCO","name":"Monaco","official_name":"Principality of Monaco","flag":"🇲🇨","region":"Europe","subregion":"Western Europe","capital":"Monaco","latlng":[43.73333333,7.4],"currency":{"code":"EUR","name":"Euro","symbol":"€"},"dialing_code":"+3","tld":".mc"},"MD":{"alpha2":"MD","alpha3":"MDA","name":"Moldova","official_name":"Republic of Moldova","flag":"🇲🇩","region":"Europe","subregion":"Eastern Europe","capital":"Chișinău","latlng":[47,29],"currency":{"code":"MDL","name":"Moldovan leu","symbol":"L"},"dialing_code":"+3","tld":".md"},"MG":{"alpha2":"MG","alpha3":"MDG","name":"Madagascar","official_name":"Republic of Madagascar","flag":"🇲🇬","region":"Africa","subregion":"Eastern Africa","capital":"Antananarivo","latlng":[-20,47],"currency":{"code":"MGA","name":"Malagasy ariary","symbol":"Ar"},"dialing_code":"+2","tld":".mg"},"MV":{"alpha2":"MV","alpha3":"MDV","name":"Maldives","official_name":"Republic of the Maldives","flag":"🇲🇻","region":"Asia","subregion":"Southern Asia","capital":"Malé","latlng":[3.25,73],"currency":{"code":"MVR","name":"Maldivian rufiyaa","symbol":".ރ"},"dialing_code":"+9","tld":".mv"},"MX":{"alpha2":"MX","alpha3":"MEX","name":"Mexico","official_name":"United Mexican States","flag":"🇲🇽","region":"Americas","subregion":"North America","capital":"Mexico City","latlng":[23,-102],"currency":{"code":"MXN","name":"Mexican peso","symbol":"$"},"dialing_code":"+5","tld":".mx"},"MH":{"alpha2":"MH","alpha3":"MHL","name":"Marshall Islands","official_name":"Republic of the Marshall Islands","flag":"🇲🇭","region":"Oceania","subregion":"Micronesia","capital":"Majuro","latlng":[9,168],"currency":{"code":"USD","name":"United States dollar","symbol":"$"},"dialing_code":"+6","tld":".mh"},"MK":{"alpha2":"MK","alpha3":"MKD","name":"North Macedonia","official_name":"Republic of North Macedonia","flag":"🇲🇰","region":"Europe","subregion":"Southeast Europe","capital":"Skopje","latlng":[41.83333333,22],"currency":{"code":"MKD","name":"denar","symbol":"den"},"dialing_code":"+3","tld":".mk"},"ML":{"alpha2":"ML","alpha3":"MLI","name":"Mali","official_name":"Republic of Mali","flag":"🇲🇱","region":"Africa","subregion":"Western Africa","capital":"Bamako","latlng":[17,-4],"currency":{"code":"XOF","name":"West African CFA franc","symbol":"Fr"},"dialing_code":"+2","tld":".ml"},"MT":{"alpha2":"MT","alpha3":"MLT","name":"Malta","official_name":"Republic of Malta","flag":"🇲🇹","region":"Europe","subregion":"Southern Europe","capital":"Valletta","latlng":[35.83333333,14.58333333],"currency":{"code":"EUR","name":"Euro","symbol":"€"},"dialing_code":"+3","tld":".mt"},"MM":{"alpha2":"MM","alpha3":"MMR","name":"Myanmar","official_name":"Republic of the Union of Myanmar","flag":"🇲🇲","region":"Asia","subregion":"South-Eastern Asia","capital":"Naypyidaw","latlng":[22,98],"currency":{"code":"MMK","name":"Burmese kyat","symbol":"Ks"},"dialing_code":"+9","tld":".mm"},"ME":{"alpha2":"ME","alpha3":"MNE","name":"Montenegro","official_name":"Montenegro","flag":"🇲🇪","region":"Europe","subregion":"Southeast Europe","capital":"Podgorica","latlng":[42.5,19.3],"currency":{"code":"EUR","name":"Euro","symbol":"€"},"dialing_code":"+3","tld":".me"},"MN":{"alpha2":"MN","alpha3":"MNG","name":"Mongolia","official_name":"Mongolia","flag":"🇲🇳","region":"Asia","subregion":"Eastern Asia","capital":"Ulan Bator","latlng":[46,105],"currency":{"code":"MNT","name":"Mongolian tögrög","symbol":"₮"},"dialing_code":"+9","tld":".mn"},"MP":{"alpha2":"MP","alpha3":"MNP","name":"Northern Mariana Islands","official_name":"Commonwealth of the Northern Mariana Islands","flag":"🇲🇵","region":"Oceania","subregion":"Micronesia","capital":"Saipan","latlng":[15.2,145.75],"currency":{"code":"USD","name":"United States dollar","symbol":"$"},"dialing_code":"+1","tld":".mp"},"MZ":{"alpha2":"MZ","alpha3":"MOZ","name":"Mozambique","official_name":"Republic of Mozambique","flag":"🇲🇿","region":"Africa","subregion":"Eastern Africa","capital":"Maputo","latlng":[-18.25,35],"currency":{"code":"MZN","name":"Mozambican metical","symbol":"MT"},"dialing_code":"+2","tld":".mz"},"MR":{"alpha2":"MR","alpha3":"MRT","name":"Mauritania","official_name":"Islamic Republic of Mauritania","flag":"🇲🇷","region":"Africa","subregion":"Western Africa","capital":"Nouakchott","latlng":[20,-12],"currency":{"code":"MRU","name":"Mauritanian ouguiya","symbol":"UM"},"dialing_code":"+2","tld":".mr"},"MS":{"alpha2":"MS","alpha3":"MSR","name":"Montserrat","official_name":"Montserrat","flag":"🇲🇸","region":"Americas","subregion":"Caribbean","capital":"Plymouth","latlng":[16.75,-62.2],"currency":{"code":"XCD","name":"Eastern Caribbean dollar","symbol":"$"},"dialing_code":"+1","tld":".ms"},"MQ":{"alpha2":"MQ","alpha3":"MTQ","name":"Martinique","official_name":"Martinique","flag":"🇲🇶","region":"Americas","subregion":"Caribbean","capital":"Fort-de-France","latlng":[14.666667,-61],"currency":{"code":"EUR","name":"Euro","symbol":"€"},"dialing_code":"+5","tld":".mq"},"MU":{"alpha2":"MU","alpha3":"MUS","name":"Mauritius","official_name":"Republic of Mauritius","flag":"🇲🇺","region":"Africa","subregion":"Eastern Africa","capital":"Port Louis","latlng":[-20.28333333,57.55],"currency":{"code":"MUR","name":"Mauritian rupee","symbol":"₨"},"dialing_code":"+2","tld":".mu"},"MW":{"alpha2":"MW","alpha3":"MWI","name":"Malawi","official_name":"Republic of Malawi","flag":"🇲🇼","region":"Africa","subregion":"Eastern Africa","capital":"Lilongwe","latlng":[-13.5,34],"currency":{"code":"MWK","name":"Malawian kwacha","symbol":"MK"},"dialing_code":"+2","tld":".mw"},"MY":{"alpha2":"MY","alpha3":"MYS","name":"Malaysia","official_name":"Malaysia","flag":"🇲🇾","region":"Asia","subregion":"South-Eastern Asia","capital":"Kuala Lumpur","latlng":[2.5,112.5],"currency":{"code":"MYR","name":"Malaysian ringgit","symbol":"RM"},"dialing_code":"+6","tld":".my"},"YT":{"alpha2":"YT","alpha3":"MYT","name":"Mayotte","official_name":"Department of Mayotte","flag":"🇾🇹","region":"Africa","subregion":"Eastern Africa","capital":"Mamoudzou","latlng":[-12.83333333,45.16666666],"currency":{"code":"EUR","name":"Euro","symbol":"€"},"dialing_code":"+2","tld":".yt"},"NA":{"alpha2":"NA","alpha3":"NAM","name":"Namibia","official_name":"Republic of Namibia","flag":"🇳🇦","region":"Africa","subregion":"Southern Africa","capital":"Windhoek","latlng":[-22,17],"currency":{"code":"NAD","name":"Namibian dollar","symbol":"$"},"dialing_code":"+2","tld":".na"},"NC":{"alpha2":"NC","alpha3":"NCL","name":"New Caledonia","official_name":"New Caledonia","flag":"🇳🇨","region":"Oceania","subregion":"Melanesia","capital":"Nouméa","latlng":[-21.5,165.5],"currency":{"code":"XPF","name":"CFP franc","symbol":"₣"},"dialing_code":"+6","tld":".nc"},"NE":{"alpha2":"NE","alpha3":"NER","name":"Niger","official_name":"Republic of Niger","flag":"🇳🇪","region":"Africa","subregion":"Western Africa","capital":"Niamey","latlng":[16,8],"currency":{"code":"XOF","name":"West African CFA franc","symbol":"Fr"},"dialing_code":"+2","tld":".ne"},"NF":{"alpha2":"NF","alpha3":"NFK","name":"Norfolk Island","official_name":"Territory of Norfolk Island","flag":"🇳🇫","region":"Oceania","subregion":"Australia and New Zealand","capital":"Kingston","latlng":[-29.03333333,167.95],"currency":{"code":"AUD","name":"Australian dollar","symbol":"$"},"dialing_code":"+6","tld":".nf"},"NG":{"alpha2":"NG","alpha3":"NGA","name":"Nigeria","official_name":"Federal Republic of Nigeria","flag":"🇳🇬","region":"Africa","subregion":"Western Africa","capital":"Abuja","latlng":[10,8],"currency":{"code":"NGN","name":"Nigerian naira","symbol":"₦"},"dialing_code":"+2","tld":".ng"},"NI":{"alpha2":"NI","alpha3":"NIC","name":"Nicaragua","official_name":"Republic of Nicaragua","flag":"🇳🇮","region":"Americas","subregion":"Central America","capital":"Managua","latlng":[13,-85],"currency":{"code":"NIO","name":"Nicaraguan córdoba","symbol":"C$"},"dialing_code":"+5","tld":".ni"},"NU":{"alpha2":"NU","alpha3":"NIU","name":"Niue","official_name":"Niue","flag":"🇳🇺","region":"Oceania","subregion":"Polynesia","capital":"Alofi","latlng":[-19.03333333,-169.86666666],"currency":{"code":"NZD","name":"New Zealand dollar","symbol":"$"},"dialing_code":"+6","tld":".nu"},"NL":{"alpha2":"NL","alpha3":"NLD","name":"Netherlands","official_name":"Kingdom of the Netherlands","flag":"🇳🇱","region":"Europe","subregion":"Western Europe","capital":"Amsterdam","latlng":[52.5,5.75],"currency":{"code":"EUR","name":"Euro","symbol":"€"},"dialing_code":"+3","tld":".nl"},"NO":{"alpha2":"NO","alpha3":"NOR","name":"Norway","official_name":"Kingdom of Norway","flag":"🇳🇴","region":"Europe","subregion":"Northern Europe","capital":"Oslo","latlng":[62,10],"currency":{"code":"NOK","name":"Norwegian krone","symbol":"kr"},"dialing_code":"+4","tld":".no"},"NP":{"alpha2":"NP","alpha3":"NPL","name":"Nepal","official_name":"Federal Democratic Republic of Nepal","flag":"🇳🇵","region":"Asia","subregion":"Southern Asia","capital":"Kathmandu","latlng":[28,84],"currency":{"code":"NPR","name":"Nepalese rupee","symbol":"₨"},"dialing_code":"+9","tld":".np"},"NR":{"alpha2":"NR","alpha3":"NRU","name":"Nauru","official_name":"Republic of Nauru","flag":"🇳🇷","region":"Oceania","subregion":"Micronesia","capital":"Yaren","latlng":[-0.53333333,166.91666666],"currency":{"code":"AUD","name":"Australian dollar","symbol":"$"},"dialing_code":"+6","tld":".nr"},"NZ":{"alpha2":"NZ","alpha3":"NZL","name":"New Zealand","official_name":"New Zealand","flag":"🇳🇿","region":"Oceania","subregion":"Australia and New Zealand","capital":"Wellington","latlng":[-41,174],"currency":{"code":"NZD","name":"New Zealand dollar","symbol":"$"},"dialing_code":"+6","tld":".nz"},"OM":{"alpha2":"OM","alpha3":"OMN","name":"Oman","official_name":"Sultanate of Oman","flag":"🇴🇲","region":"Asia","subregion":"Western Asia","capital":"Muscat","latlng":[21,57],"currency":{"code":"OMR","name":"Omani rial","symbol":"ر.ع."},"dialing_code":"+9","tld":".om"},"PK":{"alpha2":"PK","alpha3":"PAK","name":"Pakistan","official_name":"Islamic Republic of Pakistan","flag":"🇵🇰","region":"Asia","subregion":"Southern Asia","capital":"Islamabad","latlng":[30,70],"currency":{"code":"PKR","name":"Pakistani rupee","symbol":"₨"},"dialing_code":"+9","tld":".pk"},"PA":{"alpha2":"PA","alpha3":"PAN","name":"Panama","official_name":"Republic of Panama","flag":"🇵🇦","region":"Americas","subregion":"Central America","capital":"Panama City","latlng":[9,-80],"currency":{"code":"PAB","name":"Panamanian balboa","symbol":"B/."},"dialing_code":"+5","tld":".pa"},"PN":{"alpha2":"PN","alpha3":"PCN","name":"Pitcairn Islands","official_name":"Pitcairn Group of Islands","flag":"🇵🇳","region":"Oceania","subregion":"Polynesia","capital":"Adamstown","latlng":[-25.06666666,-130.1],"currency":{"code":"NZD","name":"New Zealand dollar","symbol":"$"},"dialing_code":"+6","tld":".pn"},"PE":{"alpha2":"PE","alpha3":"PER","name":"Peru","official_name":"Republic of Peru","flag":"🇵🇪","region":"Americas","subregion":"South America","capital":"Lima","latlng":[-10,-76],"currency":{"code":"PEN","name":"Peruvian sol","symbol":"S/."},"dialing_code":"+5","tld":".pe"},"PH":{"alpha2":"PH","alpha3":"PHL","name":"Philippines","official_name":"Republic of the Philippines","flag":"🇵🇭","region":"Asia","subregion":"South-Eastern Asia","capital":"Manila","latlng":[13,122],"currency":{"code":"PHP","name":"Philippine peso","symbol":"₱"},"dialing_code":"+6","tld":".ph"},"PW":{"alpha2":"PW","alpha3":"PLW","name":"Palau","official_name":"Republic of Palau","flag":"🇵🇼","region":"Oceania","subregion":"Micronesia","capital":"Ngerulmud","latlng":[7.5,134.5],"currency":{"code":"USD","name":"United States dollar","symbol":"$"},"dialing_code":"+6","tld":".pw"},"PG":{"alpha2":"PG","alpha3":"PNG","name":"Papua New Guinea","official_name":"Independent State of Papua New Guinea","flag":"🇵🇬","region":"Oceania","subregion":"Melanesia","capital":"Port Moresby","latlng":[-6,147],"currency":{"code":"PGK","name":"Papua New Guinean kina","symbol":"K"},"dialing_code":"+6","tld":".pg"},"PL":{"alpha2":"PL","alpha3":"POL","name":"Poland","official_name":"Republic of Poland","flag":"🇵🇱","region":"Europe","subregion":"Central Europe","capital":"Warsaw","latlng":[52,20],"currency":{"code":"PLN","name":"Polish złoty","symbol":"zł"},"dialing_code":"+4","tld":".pl"},"PR":{"alpha2":"PR","alpha3":"PRI","name":"Puerto Rico","official_name":"Commonwealth of Puerto Rico","flag":"🇵🇷","region":"Americas","subregion":"Caribbean","capital":"San Juan","latlng":[18.25,-66.5],"currency":{"code":"USD","name":"United States dollar","symbol":"$"},"dialing_code":"+1","tld":".pr"},"KP":{"alpha2":"KP","alpha3":"PRK","name":"North Korea","official_name":"Democratic People's Republic of Korea","flag":"🇰🇵","region":"Asia","subregion":"Eastern Asia","capital":"Pyongyang","latlng":[40,127],"currency":{"code":"KPW","name":"North Korean won","symbol":"₩"},"dialing_code":"+8","tld":".kp"},"PT":{"alpha2":"PT","alpha3":"PRT","name":"Portugal","official_name":"Portuguese Republic","flag":"🇵🇹","region":"Europe","subregion":"Southern Europe","capital":"Lisbon","latlng":[39.5,-8],"currency":{"code":"EUR","name":"Euro","symbol":"€"},"dialing_code":"+3","tld":".pt"},"PY":{"alpha2":"PY","alpha3":"PRY","name":"Paraguay","official_name":"Republic of Paraguay","flag":"🇵🇾","region":"Americas","subregion":"South America","capital":"Asunción","latlng":[-23,-58],"currency":{"code":"PYG","name":"Paraguayan guaraní","symbol":"₲"},"dialing_code":"+5","tld":".py"},"PS":{"alpha2":"PS","alpha3":"PSE","name":"Palestine","official_name":"State of Palestine","flag":"🇵🇸","region":"Asia","subregion":"Western Asia","capital":"Ramallah","latlng":[31.9,35.2],"currency":{"code":"EGP","name":"Egyptian pound","symbol":"E£"},"dialing_code":"+9","tld":".ps"},"PF":{"alpha2":"PF","alpha3":"PYF","name":"French Polynesia","official_name":"French Polynesia","flag":"🇵🇫","region":"Oceania","subregion":"Polynesia","capital":"Papeetē","latlng":[-15,-140],"currency":{"code":"XPF","name":"CFP franc","symbol":"₣"},"dialing_code":"+6","tld":".pf"},"QA":{"alpha2":"QA","alpha3":"QAT","name":"Qatar","official_name":"State of Qatar","flag":"🇶🇦","region":"Asia","subregion":"Western Asia","capital":"Doha","latlng":[25.5,51.25],"currency":{"code":"QAR","name":"Qatari riyal","symbol":"ر.ق"},"dialing_code":"+9","tld":".qa"},"RE":{"alpha2":"RE","alpha3":"REU","name":"Réunion","official_name":"Réunion Island","flag":"🇷🇪","region":"Africa","subregion":"Eastern Africa","capital":"Saint-Denis","latlng":[-21.15,55.5],"currency":{"code":"EUR","name":"Euro","symbol":"€"},"dialing_code":"+2","tld":".re"},"RO":{"alpha2":"RO","alpha3":"ROU","name":"Romania","official_name":"Romania","flag":"🇷🇴","region":"Europe","subregion":"Southeast Europe","capital":"Bucharest","latlng":[46,25],"currency":{"code":"RON","name":"Romanian leu","symbol":"lei"},"dialing_code":"+4","tld":".ro"},"RU":{"alpha2":"RU","alpha3":"RUS","name":"Russia","official_name":"Russian Federation","flag":"🇷🇺","region":"Europe","subregion":"Eastern Europe","capital":"Moscow","latlng":[60,100],"currency":{"code":"RUB","name":"Russian ruble","symbol":"₽"},"dialing_code":"+7","tld":".ru"},"RW":{"alpha2":"RW","alpha3":"RWA","name":"Rwanda","official_name":"Republic of Rwanda","flag":"🇷🇼","region":"Africa","subregion":"Eastern Africa","capital":"Kigali","latlng":[-2,30],"currency":{"code":"RWF","name":"Rwandan franc","symbol":"Fr"},"dialing_code":"+2","tld":".rw"},"SA":{"alpha2":"SA","alpha3":"SAU","name":"Saudi Arabia","official_name":"Kingdom of Saudi Arabia","flag":"🇸🇦","region":"Asia","subregion":"Western Asia","capital":"Riyadh","latlng":[25,45],"currency":{"code":"SAR","name":"Saudi riyal","symbol":"ر.س"},"dialing_code":"+9","tld":".sa"},"SD":{"alpha2":"SD","alpha3":"SDN","name":"Sudan","official_name":"Republic of the Sudan","flag":"🇸🇩","region":"Africa","subregion":"Northern Africa","capital":"Khartoum","latlng":[15,30],"currency":{"code":"SDG","name":"Sudanese pound","symbol":"PT"},"dialing_code":"+2","tld":".sd"},"SN":{"alpha2":"SN","alpha3":"SEN","name":"Senegal","official_name":"Republic of Senegal","flag":"🇸🇳","region":"Africa","subregion":"Western Africa","capital":"Dakar","latlng":[14,-14],"currency":{"code":"XOF","name":"West African CFA franc","symbol":"Fr"},"dialing_code":"+2","tld":".sn"},"SG":{"alpha2":"SG","alpha3":"SGP","name":"Singapore","official_name":"Republic of Singapore","flag":"🇸🇬","region":"Asia","subregion":"South-Eastern Asia","capital":"Singapore","latlng":[1.36666666,103.8],"currency":{"code":"SGD","name":"Singapore dollar","symbol":"$"},"dialing_code":"+6","tld":".sg"},"GS":{"alpha2":"GS","alpha3":"SGS","name":"South Georgia","official_name":"South Georgia and the South Sandwich Islands","flag":"🇬🇸","region":"Antarctic","subregion":null,"capital":"King Edward Point","latlng":[-54.5,-37],"currency":{"code":"SHP","name":"Saint Helena pound","symbol":"£"},"dialing_code":"+5","tld":".gs"},"SJ":{"alpha2":"SJ","alpha3":"SJM","name":"Svalbard and Jan Mayen","official_name":"Svalbard og Jan Mayen","flag":"🇸🇯","region":"Europe","subregion":"Northern Europe","capital":"Longyearbyen","latlng":[78,20],"currency":{"code":"NOK","name":"krone","symbol":"kr"},"dialing_code":"+4","tld":".sj"},"SB":{"alpha2":"SB","alpha3":"SLB","name":"Solomon Islands","official_name":"Solomon Islands","flag":"🇸🇧","region":"Oceania","subregion":"Melanesia","capital":"Honiara","latlng":[-8,159],"currency":{"code":"SBD","name":"Solomon Islands dollar","symbol":"$"},"dialing_code":"+6","tld":".sb"},"SL":{"alpha2":"SL","alpha3":"SLE","name":"Sierra Leone","official_name":"Republic of Sierra Leone","flag":"🇸🇱","region":"Africa","subregion":"Western Africa","capital":"Freetown","latlng":[8.5,-11.5],"currency":{"code":"SLL","name":"Sierra Leonean leone","symbol":"Le"},"dialing_code":"+2","tld":".sl"},"SV":{"alpha2":"SV","alpha3":"SLV","name":"El Salvador","official_name":"Republic of El Salvador","flag":"🇸🇻","region":"Americas","subregion":"Central America","capital":"San Salvador","latlng":[13.83333333,-88.91666666],"currency":{"code":"USD","name":"United States dollar","symbol":"$"},"dialing_code":"+5","tld":".sv"},"SM":{"alpha2":"SM","alpha3":"SMR","name":"San Marino","official_name":"Most Serene Republic of San Marino","flag":"🇸🇲","region":"Europe","subregion":"Southern Europe","capital":"City of San Marino","latlng":[43.76666666,12.41666666],"currency":{"code":"EUR","name":"Euro","symbol":"€"},"dialing_code":"+3","tld":".sm"},"SO":{"alpha2":"SO","alpha3":"SOM","name":"Somalia","official_name":"Federal Republic of Somalia","flag":"🇸🇴","region":"Africa","subregion":"Eastern Africa","capital":"Mogadishu","latlng":[10,49],"currency":{"code":"SOS","name":"Somali shilling","symbol":"Sh"},"dialing_code":"+2","tld":".so"},"PM":{"alpha2":"PM","alpha3":"SPM","name":"Saint Pierre and Miquelon","official_name":"Saint Pierre and Miquelon","flag":"🇵🇲","region":"Americas","subregion":"North America","capital":"Saint-Pierre","latlng":[46.83333333,-56.33333333],"currency":{"code":"EUR","name":"Euro","symbol":"€"},"dialing_code":"+5","tld":".pm"},"RS":{"alpha2":"RS","alpha3":"SRB","name":"Serbia","official_name":"Republic of Serbia","flag":"🇷🇸","region":"Europe","subregion":"Southeast Europe","capital":"Belgrade","latlng":[44,21],"currency":{"code":"RSD","name":"Serbian dinar","symbol":"дин."},"dialing_code":"+3","tld":".rs"},"SS":{"alpha2":"SS","alpha3":"SSD","name":"South Sudan","official_name":"Republic of South Sudan","flag":"🇸🇸","region":"Africa","subregion":"Middle Africa","capital":"Juba","latlng":[7,30],"currency":{"code":"SSP","name":"South Sudanese pound","symbol":"£"},"dialing_code":"+2","tld":".ss"},"ST":{"alpha2":"ST","alpha3":"STP","name":"São Tomé and Príncipe","official_name":"Democratic Republic of São Tomé and Príncipe","flag":"🇸🇹","region":"Africa","subregion":"Middle Africa","capital":"São Tomé","latlng":[1,7],"currency":{"code":"STN","name":"São Tomé and Príncipe dobra","symbol":"Db"},"dialing_code":"+2","tld":".st"},"SR":{"alpha2":"SR","alpha3":"SUR","name":"Suriname","official_name":"Republic of Suriname","flag":"🇸🇷","region":"Americas","subregion":"South America","capital":"Paramaribo","latlng":[4,-56],"currency":{"code":"SRD","name":"Surinamese dollar","symbol":"$"},"dialing_code":"+5","tld":".sr"},"SK":{"alpha2":"SK","alpha3":"SVK","name":"Slovakia","official_name":"Slovak Republic","flag":"🇸🇰","region":"Europe","subregion":"Central Europe","capital":"Bratislava","latlng":[48.66666666,19.5],"currency":{"code":"EUR","name":"Euro","symbol":"€"},"dialing_code":"+4","tld":".sk"},"SI":{"alpha2":"SI","alpha3":"SVN","name":"Slovenia","official_name":"Republic of Slovenia","flag":"🇸🇮","region":"Europe","subregion":"Central Europe","capital":"Ljubljana","latlng":[46.11666666,14.81666666],"currency":{"code":"EUR","name":"Euro","symbol":"€"},"dialing_code":"+3","tld":".si"},"SE":{"alpha2":"SE","alpha3":"SWE","name":"Sweden","official_name":"Kingdom of Sweden","flag":"🇸🇪","region":"Europe","subregion":"Northern Europe","capital":"Stockholm","latlng":[62,15],"currency":{"code":"SEK","name":"Swedish krona","symbol":"kr"},"dialing_code":"+4","tld":".se"},"SZ":{"alpha2":"SZ","alpha3":"SWZ","name":"Eswatini","official_name":"Kingdom of Eswatini","flag":"🇸🇿","region":"Africa","subregion":"Southern Africa","capital":"Lobamba","latlng":[-26.5,31.5],"currency":{"code":"SZL","name":"Swazi lilangeni","symbol":"L"},"dialing_code":"+2","tld":".sz"},"SX":{"alpha2":"SX","alpha3":"SXM","name":"Sint Maarten","official_name":"Sint Maarten","flag":"🇸🇽","region":"Americas","subregion":"Caribbean","capital":"Philipsburg","latlng":[18.033333,-63.05],"currency":{"code":"ANG","name":"Netherlands Antillean guilder","symbol":"ƒ"},"dialing_code":"+1","tld":".sx"},"SC":{"alpha2":"SC","alpha3":"SYC","name":"Seychelles","official_name":"Republic of Seychelles","flag":"🇸🇨","region":"Africa","subregion":"Eastern Africa","capital":"Victoria","latlng":[-4.58333333,55.66666666],"currency":{"code":"SCR","name":"Seychellois rupee","symbol":"₨"},"dialing_code":"+2","tld":".sc"},"SY":{"alpha2":"SY","alpha3":"SYR","name":"Syria","official_name":"Syrian Arab Republic","flag":"🇸🇾","region":"Asia","subregion":"Western Asia","capital":"Damascus","latlng":[35,38],"currency":{"code":"SYP","name":"Syrian pound","symbol":"£"},"dialing_code":"+9","tld":".sy"},"TC":{"alpha2":"TC","alpha3":"TCA","name":"Turks and Caicos Islands","official_name":"Turks and Caicos Islands","flag":"🇹🇨","region":"Americas","subregion":"Caribbean","capital":"Cockburn Town","latlng":[21.75,-71.58333333],"currency":{"code":"USD","name":"United States dollar","symbol":"$"},"dialing_code":"+1","tld":".tc"},"TD":{"alpha2":"TD","alpha3":"TCD","name":"Chad","official_name":"Republic of Chad","flag":"🇹🇩","region":"Africa","subregion":"Middle Africa","capital":"N'Djamena","latlng":[15,19],"currency":{"code":"XAF","name":"Central African CFA franc","symbol":"Fr"},"dialing_code":"+2","tld":".td"},"TG":{"alpha2":"TG","alpha3":"TGO","name":"Togo","official_name":"Togolese Republic","flag":"🇹🇬","region":"Africa","subregion":"Western Africa","capital":"Lomé","latlng":[8,1.16666666],"currency":{"code":"XOF","name":"West African CFA franc","symbol":"Fr"},"dialing_code":"+2","tld":".tg"},"TH":{"alpha2":"TH","alpha3":"THA","name":"Thailand","official_name":"Kingdom of Thailand","flag":"🇹🇭","region":"Asia","subregion":"South-Eastern Asia","capital":"Bangkok","latlng":[15,100],"currency":{"code":"THB","name":"Thai baht","symbol":"฿"},"dialing_code":"+6","tld":".th"},"TJ":{"alpha2":"TJ","alpha3":"TJK","name":"Tajikistan","official_name":"Republic of Tajikistan","flag":"🇹🇯","region":"Asia","subregion":"Central Asia","capital":"Dushanbe","latlng":[39,71],"currency":{"code":"TJS","name":"Tajikistani somoni","symbol":"ЅМ"},"dialing_code":"+9","tld":".tj"},"TK":{"alpha2":"TK","alpha3":"TKL","name":"Tokelau","official_name":"Tokelau","flag":"🇹🇰","region":"Oceania","subregion":"Polynesia","capital":"Fakaofo","latlng":[-9,-172],"currency":{"code":"NZD","name":"New Zealand dollar","symbol":"$"},"dialing_code":"+6","tld":".tk"},"TM":{"alpha2":"TM","alpha3":"TKM","name":"Turkmenistan","official_name":"Turkmenistan","flag":"🇹🇲","region":"Asia","subregion":"Central Asia","capital":"Ashgabat","latlng":[40,60],"currency":{"code":"TMT","name":"Turkmenistan manat","symbol":"m"},"dialing_code":"+9","tld":".tm"},"TL":{"alpha2":"TL","alpha3":"TLS","name":"Timor-Leste","official_name":"Democratic Republic of Timor-Leste","flag":"🇹🇱","region":"Asia","subregion":"South-Eastern Asia","capital":"Dili","latlng":[-8.83333333,125.91666666],"currency":{"code":"USD","name":"United States dollar","symbol":"$"},"dialing_code":"+6","tld":".tl"},"TO":{"alpha2":"TO","alpha3":"TON","name":"Tonga","official_name":"Kingdom of Tonga","flag":"🇹🇴","region":"Oceania","subregion":"Polynesia","capital":"Nuku'alofa","latlng":[-20,-175],"currency":{"code":"TOP","name":"Tongan paʻanga","symbol":"T$"},"dialing_code":"+6","tld":".to"},"TT":{"alpha2":"TT","alpha3":"TTO","name":"Trinidad and Tobago","official_name":"Republic of Trinidad and Tobago","flag":"🇹🇹","region":"Americas","subregion":"Caribbean","capital":"Port of Spain","latlng":[11,-61],"currency":{"code":"TTD","name":"Trinidad and Tobago dollar","symbol":"$"},"dialing_code":"+1","tld":".tt"},"TN":{"alpha2":"TN","alpha3":"TUN","name":"Tunisia","official_name":"Tunisian Republic","flag":"🇹🇳","region":"Africa","subregion":"Northern Africa","capital":"Tunis","latlng":[34,9],"currency":{"code":"TND","name":"Tunisian dinar","symbol":"د.ت"},"dialing_code":"+2","tld":".tn"},"TR":{"alpha2":"TR","alpha3":"TUR","name":"Türkiye","official_name":"Republic of Türkiye","flag":"🇹🇷","region":"Asia","subregion":"Western Asia","capital":"Ankara","latlng":[39,35],"currency":{"code":"TRY","name":"Turkish lira","symbol":"₺"},"dialing_code":"+9","tld":".tr"},"TV":{"alpha2":"TV","alpha3":"TUV","name":"Tuvalu","official_name":"Tuvalu","flag":"🇹🇻","region":"Oceania","subregion":"Polynesia","capital":"Funafuti","latlng":[-8,178],"currency":{"code":"AUD","name":"Australian dollar","symbol":"$"},"dialing_code":"+6","tld":".tv"},"TW":{"alpha2":"TW","alpha3":"TWN","name":"Taiwan","official_name":"Republic of China (Taiwan)","flag":"🇹🇼","region":"Asia","subregion":"Eastern Asia","capital":"Taipei","latlng":[23.5,121],"currency":{"code":"TWD","name":"New Taiwan dollar","symbol":"$"},"dialing_code":"+8","tld":".tw"},"TZ":{"alpha2":"TZ","alpha3":"TZA","name":"Tanzania","official_name":"United Republic of Tanzania","flag":"🇹🇿","region":"Africa","subregion":"Eastern Africa","capital":"Dodoma","latlng":[-6,35],"currency":{"code":"TZS","name":"Tanzanian shilling","symbol":"Sh"},"dialing_code":"+2","tld":".tz"},"UG":{"alpha2":"UG","alpha3":"UGA","name":"Uganda","official_name":"Republic of Uganda","flag":"🇺🇬","region":"Africa","subregion":"Eastern Africa","capital":"Kampala","latlng":[1,32],"currency":{"code":"UGX","name":"Ugandan shilling","symbol":"Sh"},"dialing_code":"+2","tld":".ug"},"UA":{"alpha2":"UA","alpha3":"UKR","name":"Ukraine","official_name":"Ukraine","flag":"🇺🇦","region":"Europe","subregion":"Eastern Europe","capital":"Kyiv","latlng":[49,32],"currency":{"code":"UAH","name":"Ukrainian hryvnia","symbol":"₴"},"dialing_code":"+3","tld":".ua"},"UM":{"alpha2":"UM","alpha3":"UMI","name":"United States Minor Outlying Islands","official_name":"United States Minor Outlying Islands","flag":"🇺🇲","region":"Americas","subregion":"North America","capital":null,"latlng":[19.3,166.633333],"currency":{"code":"USD","name":"United States dollar","symbol":"$"},"dialing_code":"+2","tld":".us"},"UY":{"alpha2":"UY","alpha3":"URY","name":"Uruguay","official_name":"Oriental Republic of Uruguay","flag":"🇺🇾","region":"Americas","subregion":"South America","capital":"Montevideo","latlng":[-33,-56],"currency":{"code":"UYU","name":"Uruguayan peso","symbol":"$"},"dialing_code":"+5","tld":".uy"},"US":{"alpha2":"US","alpha3":"USA","name":"United States","official_name":"United States of America","flag":"🇺🇸","region":"Americas","subregion":"North America","capital":"Washington D.C.","latlng":[38,-97],"currency":{"code":"USD","name":"United States dollar","symbol":"$"},"dialing_code":"+1","tld":".us"},"UZ":{"alpha2":"UZ","alpha3":"UZB","name":"Uzbekistan","official_name":"Republic of Uzbekistan","flag":"🇺🇿","region":"Asia","subregion":"Central Asia","capital":"Tashkent","latlng":[41,64],"currency":{"code":"UZS","name":"Uzbekistani soʻm","symbol":"so'm"},"dialing_code":"+9","tld":".uz"},"VA":{"alpha2":"VA","alpha3":"VAT","name":"Vatican City","official_name":"Vatican City State","flag":"🇻🇦","region":"Europe","subregion":"Southern Europe","capital":"Vatican City","latlng":[41.9,12.45],"currency":{"code":"EUR","name":"Euro","symbol":"€"},"dialing_code":"+3","tld":".va"},"VC":{"alpha2":"VC","alpha3":"VCT","name":"Saint Vincent and the Grenadines","official_name":"Saint Vincent and the Grenadines","flag":"🇻🇨","region":"Americas","subregion":"Caribbean","capital":"Kingstown","latlng":[13.25,-61.2],"currency":{"code":"XCD","name":"Eastern Caribbean dollar","symbol":"$"},"dialing_code":"+1","tld":".vc"},"VE":{"alpha2":"VE","alpha3":"VEN","name":"Venezuela","official_name":"Bolivarian Republic of Venezuela","flag":"🇻🇪","region":"Americas","subregion":"South America","capital":"Caracas","latlng":[8,-66],"currency":{"code":"VES","name":"Venezuelan bolívar soberano","symbol":"Bs.S."},"dialing_code":"+5","tld":".ve"},"VG":{"alpha2":"VG","alpha3":"VGB","name":"British Virgin Islands","official_name":"Virgin Islands","flag":"🇻🇬","region":"Americas","subregion":"Caribbean","capital":"Road Town","latlng":[18.431383,-64.62305],"currency":{"code":"USD","name":"United States dollar","symbol":"$"},"dialing_code":"+1","tld":".vg"},"VI":{"alpha2":"VI","alpha3":"VIR","name":"United States Virgin Islands","official_name":"Virgin Islands of the United States","flag":"🇻🇮","region":"Americas","subregion":"Caribbean","capital":"Charlotte Amalie","latlng":[18.35,-64.933333],"currency":{"code":"USD","name":"United States dollar","symbol":"$"},"dialing_code":"+1","tld":".vi"},"VN":{"alpha2":"VN","alpha3":"VNM","name":"Vietnam","official_name":"Socialist Republic of Vietnam","flag":"🇻🇳","region":"Asia","subregion":"South-Eastern Asia","capital":"Hanoi","latlng":[16.16666666,107.83333333],"currency":{"code":"VND","name":"Vietnamese đồng","symbol":"₫"},"dialing_code":"+8","tld":".vn"},"VU":{"alpha2":"VU","alpha3":"VUT","name":"Vanuatu","official_name":"Republic of Vanuatu","flag":"🇻🇺","region":"Oceania","subregion":"Melanesia","capital":"Port Vila","latlng":[-16,167],"currency":{"code":"VUV","name":"Vanuatu vatu","symbol":"Vt"},"dialing_code":"+6","tld":".vu"},"WF":{"alpha2":"WF","alpha3":"WLF","name":"Wallis and Futuna","official_name":"Territory of the Wallis and Futuna Islands","flag":"🇼🇫","region":"Oceania","subregion":"Polynesia","capital":"Mata-Utu","latlng":[-13.3,-176.2],"currency":{"code":"XPF","name":"CFP franc","symbol":"₣"},"dialing_code":"+6","tld":".wf"},"WS":{"alpha2":"WS","alpha3":"WSM","name":"Samoa","official_name":"Independent State of Samoa","flag":"🇼🇸","region":"Oceania","subregion":"Polynesia","capital":"Apia","latlng":[-13.58333333,-172.33333333],"currency":{"code":"WST","name":"Samoan tālā","symbol":"T"},"dialing_code":"+6","tld":".ws"},"YE":{"alpha2":"YE","alpha3":"YEM","name":"Yemen","official_name":"Republic of Yemen","flag":"🇾🇪","region":"Asia","subregion":"Western Asia","capital":"Sana'a","latlng":[15,48],"currency":{"code":"YER","name":"Yemeni rial","symbol":"﷼"},"dialing_code":"+9","tld":".ye"},"ZA":{"alpha2":"ZA","alpha3":"ZAF","name":"South Africa","official_name":"Republic of South Africa","flag":"🇿🇦","region":"Africa","subregion":"Southern Africa","capital":"Pretoria","latlng":[-29,24],"currency":{"code":"ZAR","name":"South African rand","symbol":"R"},"dialing_code":"+2","tld":".za"},"ZM":{"alpha2":"ZM","alpha3":"ZMB","name":"Zambia","official_name":"Republic of Zambia","flag":"🇿🇲","region":"Africa","subregion":"Eastern Africa","capital":"Lusaka","latlng":[-15,30],"currency":{"code":"ZMW","name":"Zambian kwacha","symbol":"ZK"},"dialing_code":"+2","tld":".zm"},"ZW":{"alpha2":"ZW","alpha3":"ZWE","name":"Zimbabwe","official_name":"Republic of Zimbabwe","flag":"🇿🇼","region":"Africa","subregion":"Eastern Africa","capital":"Harare","latlng":[-20,30],"currency":{"code":"BWP","name":"Botswana pula","symbol":"P"},"dialing_code":"+2","tld":".zw"}}